three_d_fin/3DFinconfig.ini
three_d_fin/__about__.py
three_d_fin/__init__.py
three_d_fin/__main__.py
three_d_fin/cloudcompare/__init__.py
three_d_fin/cloudcompare/plugin.py
three_d_fin/cloudcompare/plugin_processing.py
three_d_fin/cloudcompare/plugin_progress.py
three_d_fin/cloudcompare/assets/3dfin_color_scale.xml
three_d_fin/cloudcompare/assets/3dfin_logo_plugin.png
three_d_fin/documentation/documentation.pdf
three_d_fin/gui/.gitignore
three_d_fin/gui/__init__.py
three_d_fin/gui/application.py
three_d_fin/gui/expert_dlg.py
three_d_fin/gui/gui_ressources_rc.py
three_d_fin/gui/main_window.py
three_d_fin/processing/__init__.py
three_d_fin/processing/abstract_processing.py
three_d_fin/processing/configuration.py
three_d_fin/processing/io.py
three_d_fin/processing/progress.py
three_d_fin/processing/standalone_processing.py
3dfin-0.6.0.dist-info/METADATA
3dfin-0.6.0.dist-info/WHEEL
3dfin-0.6.0.dist-info/entry_points.txt
3dfin-0.6.0.dist-info/licenses/LICENSE
3dfin-0.6.0.dist-info/RECORD
