Metadata-Version: 2.4
Name: 3DFin
Version: 0.6.0
Summary: Automatic dendrometry and forest inventory for terrestrial point clouds, application package
Project-URL: Documentation, https://github.com/3DFin/3DFin#README.md
Project-URL: Issues, https://github.com/3DFin/3DFin/issues
Project-URL: Source, https://github.com/3DFin/3DFin
Author-email: Carlos Cabo <carloscabo@uniovi.es>, Diego Laino <diegolainor@gmail.com>
License-Expression: GPL-3.0-or-later
License-File: LICENSE
Keywords: forestry,lidar,tls
Classifier: Development Status :: 4 - Beta
Classifier: Intended Audience :: Science/Research
Classifier: Programming Language :: Python
Classifier: Programming Language :: Python :: 3.10
Classifier: Programming Language :: Python :: 3.11
Classifier: Programming Language :: Python :: 3.12
Classifier: Programming Language :: Python :: 3.13
Classifier: Programming Language :: Python :: Implementation :: CPython
Classifier: Topic :: Scientific/Engineering
Classifier: Topic :: Scientific/Engineering :: GIS
Requires-Python: >=3.10
Requires-Dist: dendromatics[dendroptimized]==0.7.0
Requires-Dist: lazrs~=0.8.0
Requires-Dist: pandas~=2.3.0
Requires-Dist: pydantic~=1.10
Requires-Dist: pyside6>=6.8.1
Requires-Dist: xlsxwriter~=3.2.4
